litmgr/__init__.py
litmgr-0.1.0.dist-info/licenses/LICENSE
litmgr-0.1.0.dist-info/METADATA
litmgr-0.1.0.dist-info/WHEEL
litmgr-0.1.0.dist-info/top_level.txt
litmgr-0.1.0.dist-info/RECORD
