Metadata-Version: 2.4
Name: litmgr
Version: 0.1.0
Summary: An automated literature manager
Author-email: Magic Squash <magic_squash@petalmail.com>
Requires-Python: >=3.10
License-File: LICENSE
Requires-Dist: arxiv>=2.2.0
Dynamic: license-file
